<?xml version="1.0" encoding="UTF-8"?>
<?xml-stylesheet type="text/xsl" href="../transformationsXSLT/test.xslt"?>
<grilleSudoku xmlns:xsi="http://www.w3.org/2001/XMLSchema-instance">
    
  <region numero="1">
    <case ligne="1" colonne="1" fixe="true" region="1">8</case>
    <case ligne="1" colonne="2" fixe="true" region="1">1</case>
    <case ligne="2" colonne="3" fixe="true" region="1">6</case>
    <case ligne="3" colonne="1" fixe="true" region="1">4</case>
  </region>
  
  <region numero="2">
    <case ligne="1" colonne="5" fixe="true" region="2">2</case>
    <case ligne="2" colonne="4" fixe="true" region="2">8</case>
    <case ligne="3" colonne="6" fixe="true" region="2">1</case>
  </region>
  
  <region numero="3">
    <case ligne="1" colonne="8" fixe="true" region="3">4</case>
    <case ligne="2" colonne="9" fixe="true" region="3">2</case>
    <case ligne="3" colonne="7" fixe="true" region="3">8</case>
  </region>
  
  <region numero="4">
    <case ligne="4" colonne="2" fixe="true" region="4">2</case>
    <case ligne="5" colonne="3" fixe="true" region="4">5</case>
    <case ligne="6" colonne="1" fixe="true" region="4">3</case>
  </region>
  
  <region numero="5">
    <case ligne="4" colonne="4" fixe="true" region="5">7</case>
    <case ligne="6" colonne="6" fixe="true" region="5">2</case>
  </region>
  
  <region numero="6">
    <case ligne="4" colonne="8" fixe="true" region="6">3</case>
    <case ligne="5" colonne="9" fixe="true" region="6">1</case>
    <case ligne="6" colonne="7" fixe="true" region="6">9</case>
  </region>
  
  <region numero="7">
    <case ligne="7" colonne="2" fixe="true" region="7">3</case>
    <case ligne="8" colonne="3" fixe="true" region="7">9</case>
    <case ligne="9" colonne="1" fixe="true" region="7">1</case>
  </region>
  
  <region numero="8">
    <case ligne="7" colonne="4" fixe="true" region="8">1</case>
    <case ligne="8" colonne="5" fixe="true" region="8">8</case>
    <case ligne="9" colonne="6" fixe="true" region="8">3</case>
  </region>
  
  <region numero="9">
    <case ligne="7" colonne="8" fixe="true" region="9">5</case>
    <case ligne="8" colonne="9" fixe="true" region="9">3</case>
    <case ligne="9" colonne="7" fixe="true" region="9">2</case>
    <case ligne="9" colonne="8" fixe="true" region="9">8</case>
  </region>
  
</grilleSudoku>